json_array_file/__init__.py
json_array_file-0.1.dist-info/LICENCE
json_array_file-0.1.dist-info/METADATA
json_array_file-0.1.dist-info/WHEEL
json_array_file-0.1.dist-info/top_level.txt
json_array_file-0.1.dist-info/RECORD
