Metadata-Version: 2.1
Name: json-array-file
Version: 0.1
Summary: Memory efficient JSON Array file writer
Home-page: https://github.com/milano-slesarik/json-array-file
Author: Milan Slesarik
Author-email: milslesarik@gmail.com
License: MIT
Platform: UNKNOWN
License-File: LICENCE
